GEMAP/__init__.py
GEMAP/data/NIHMS1530136Simple.xlsx
GEMAP/data/allGenesWithIds.csv
GEMAP/data/df_3_SS_he_uniform_relu_mae_adam_1_64_1024.pkl
GEMAP/data/peakID_info.csv
GEMAP-0.0.30.dist-info/METADATA
GEMAP-0.0.30.dist-info/WHEEL
GEMAP-0.0.30.dist-info/top_level.txt
GEMAP-0.0.30.dist-info/RECORD
