Metadata-Version: 2.1
Name: GEMAP
Version: 0.0.30
Summary: Regression-Based Approaches to Predict Cellular Metabolomic Profiles from Transcriptomic Data
Home-page: https://github.com/krishan57gupta/GEMAP
Author: Krishan Gupta, Kaifu Chen
Author-email: krishan57gupta@gmail.com
Classifier: Programming Language :: Python :: 3
Classifier: License :: OSI Approved :: MIT License
Classifier: Operating System :: OS Independent
Requires-Python: >=3.6
